// converted by version 1.3
// on Tue Nov 27 17:44:42 CET 2007

.package benchs/jcapi/javacard_security/deskey/getkey {
	.aid 0x4D:0x45:0x53:0x55:0x52:0x45:0x5F:0x67:0x6B:0x65:0x79;
	.version 1.0;

	.imports {
		0x4D:0x45:0x53:0x55:0x52:0x45 1.0;		//benchs/lib/templates
		0xA0:0x0:0x0:0x0:0x62:0x0:0x1 1.0;		//java/lang
		0xA0:0x0:0x0:0x0:0x62:0x1:0x2 1.1;		//javacard/security
		0xA0:0x0:0x0:0x0:0x62:0x1:0x1 1.0;		//javacard/framework
	}

	.applet {
		0x4D:0x45:0x53:0x55:0x52:0x45:0x5F:0x67:0x6B:0x65:0x79:0x1 GetKeyTestApplet;
	}

	.constantPool {
		// 0
		instanceFieldRef GetKeyTestApplet GetKeyTestApplet$1/this$0;
		// 1
		instanceFieldRef GetKeyTestApplet GetKeyTestApplet$2/this$0;
		// 2
		instanceFieldRef byte[] GetKeyTestApplet/data;
		// 3
		instanceFieldRef 0.1 0.10.33;		// reference benchs/lib/templates/KeyTemplateApplet.dummyInterface
		// 4
		instanceFieldRef 2.10 0.10.35;		// reference benchs/lib/templates/KeyTemplateApplet.desKey
		// 5
		classRef 0.1;		// benchs/lib/templates/DummyInterface
		// 6
		staticMethodRef 0.7.0()V;		// benchs/lib/templates/TestCase.<init>()V
		// 7
		staticMethodRef GetKeyTestApplet/access$3(Lbenchs/jcapi/javacard_security/deskey/getkey/GetKeyTestApplet;)Ljavacard/security/DESKey;;
			.descriptor	Ljavacard/security/DESKey;	2.10;

		// 8
		classRef 2.10;		// javacard/security/DESKey
		// 9
		staticMethodRef 0.10.0()V;		// benchs/lib/templates/KeyTemplateApplet.<init>()V
		// 10
		staticMethodRef 3.8.13(SB)[B;		// javacard/framework/JCSystem.makeTransientByteArray(SB)[B
		// 11
		staticMethodRef GetKeyTestApplet/access$0(Lbenchs/jcapi/javacard_security/deskey/getkey/GetKeyTestApplet;[B)V;
		// 12
		classRef GetKeyTestApplet;
		// 13
		staticMethodRef GetKeyTestApplet/<init>()V;
		// 14
		virtualMethodRef 0.10.1()V;		// register()V
		// 15
		classRef 0.7;		// benchs/lib/templates/TestCase
		// 16
		classRef GetKeyTestApplet$1;
		// 17
		staticMethodRef GetKeyTestApplet$1/<init>(Lbenchs/jcapi/javacard_security/deskey/getkey/GetKeyTestApplet;)V;
		// 18
		classRef GetKeyTestApplet$2;
		// 19
		staticMethodRef GetKeyTestApplet$2/<init>(Lbenchs/jcapi/javacard_security/deskey/getkey/GetKeyTestApplet;)V;
		// 20
		virtualMethodRef 0.10.9([B)V;		// init([B)V
		// 21
		staticMethodRef GetKeyTestApplet/access$1(Lbenchs/jcapi/javacard_security/deskey/getkey/GetKeyTestApplet;)Lbenchs/lib/templates/DummyInterface;;
			.descriptor	Lbenchs/lib/templates/DummyInterface;	0.1;

		// 22
		staticMethodRef GetKeyTestApplet/access$2(Lbenchs/jcapi/javacard_security/deskey/getkey/GetKeyTestApplet;)[B;
	}

	.class final GetKeyTestApplet$1 extends 0.7 {		// extends benchs/lib/templates/TestCase

		.fields {
			final GetKeyTestApplet this$0 0;		// Lbenchs/jcapi/javacard_security/deskey/getkey/GetKeyTestApplet;
		}

		.publicMethodTable 2 {
			equals(Ljava/lang/Object;)Z;
			setUp([BS)V;
			setUp([B)V;
			cleanUp([B)V;
			isUseInnerCounter()Z;
			setUseInnerCounter(Z)V;
			run([B)V;
		}

		.packageMethodTable 0 {
		}

		.method  <init>(Lbenchs/jcapi/javacard_security/deskey/getkey/GetKeyTestApplet;)V {
			.stack 2;
			.locals 0;

				L0:	aload_0;
					aload_1;
					putfield_a 0;		// reference benchs/jcapi/javacard_security/deskey/getkey/GetKeyTestApplet$1.this$0
					aload_0;
					invokespecial 6;		// benchs/lib/templates/TestCase.<init>()V
					return;
		}

		.method public setUp([B)V 2 {
			.stack 2;
			.locals 0;

				L0:	getfield_a_this 0;		// reference benchs/jcapi/javacard_security/deskey/getkey/GetKeyTestApplet$1.this$0
					aload_1;
					invokestatic 11;		// benchs/jcapi/javacard_security/deskey/getkey/GetKeyTestApplet.access$0(Lbenchs/jcapi/javacard_security/deskey/getkey/GetKeyTestApplet;[B)V
					return;
		}

		.method public run([B)V 6 {
			.stack 3;
			.locals 0;

				L0:	getfield_a_this 0;		// reference benchs/jcapi/javacard_security/deskey/getkey/GetKeyTestApplet$1.this$0
					invokestatic 21;		// benchs/jcapi/javacard_security/deskey/getkey/GetKeyTestApplet.access$1(Lbenchs/jcapi/javacard_security/deskey/getkey/GetKeyTestApplet;)Lbenchs/lib/templates/DummyInterface;
					getfield_a_this 0;		// reference benchs/jcapi/javacard_security/deskey/getkey/GetKeyTestApplet$1.this$0
					invokestatic 22;		// benchs/jcapi/javacard_security/deskey/getkey/GetKeyTestApplet.access$2(Lbenchs/jcapi/javacard_security/deskey/getkey/GetKeyTestApplet;)[B
					sconst_0;
					invokeinterface 3 5 3;		// benchs/lib/templates/DummyInterface
					return;
		}

	}

	.class final GetKeyTestApplet$2 extends 0.7 {		// extends benchs/lib/templates/TestCase

		.fields {
			final GetKeyTestApplet this$0 0;		// Lbenchs/jcapi/javacard_security/deskey/getkey/GetKeyTestApplet;
		}

		.publicMethodTable 2 {
			equals(Ljava/lang/Object;)Z;
			setUp([BS)V;
			setUp([B)V;
			cleanUp([B)V;
			isUseInnerCounter()Z;
			setUseInnerCounter(Z)V;
			run([B)V;
		}

		.packageMethodTable 0 {
		}

		.method  <init>(Lbenchs/jcapi/javacard_security/deskey/getkey/GetKeyTestApplet;)V {
			.stack 2;
			.locals 0;

				L0:	aload_0;
					aload_1;
					putfield_a 1;		// reference benchs/jcapi/javacard_security/deskey/getkey/GetKeyTestApplet$2.this$0
					aload_0;
					invokespecial 6;		// benchs/lib/templates/TestCase.<init>()V
					return;
		}

		.method public setUp([B)V 2 {
			.stack 2;
			.locals 0;

				L0:	getfield_a_this 1;		// reference benchs/jcapi/javacard_security/deskey/getkey/GetKeyTestApplet$2.this$0
					aload_1;
					invokestatic 11;		// benchs/jcapi/javacard_security/deskey/getkey/GetKeyTestApplet.access$0(Lbenchs/jcapi/javacard_security/deskey/getkey/GetKeyTestApplet;[B)V
					return;
		}

		.method public run([B)V 6 {
			.stack 3;
			.locals 0;

				L0:	getfield_a_this 1;		// reference benchs/jcapi/javacard_security/deskey/getkey/GetKeyTestApplet$2.this$0
					invokestatic 7;		// benchs/jcapi/javacard_security/deskey/getkey/GetKeyTestApplet.access$3(Lbenchs/jcapi/javacard_security/deskey/getkey/GetKeyTestApplet;)Ljavacard/security/DESKey;
					getfield_a_this 1;		// reference benchs/jcapi/javacard_security/deskey/getkey/GetKeyTestApplet$2.this$0
					invokestatic 22;		// benchs/jcapi/javacard_security/deskey/getkey/GetKeyTestApplet.access$2(Lbenchs/jcapi/javacard_security/deskey/getkey/GetKeyTestApplet;)[B
					sconst_0;
					invokeinterface 3 8 4;		// javacard/security/DESKey
					pop;
					return;
		}

	}

	.class public GetKeyTestApplet 0 extends 0.10 {		// extends benchs/lib/templates/KeyTemplateApplet

		.fields {
			private byte[] data 0;		// [B
		}

		.publicMethodTable 8 {
			equals(Ljava/lang/Object;)Z;
			register()V;
			register([BSB)V;
			selectingApplet()Z;
			deselect()V;
			getShareableInterfaceObject(Ljavacard/framework/AID;B)Ljavacard/framework/Shareable;;
			select()Z;
			process(Ljavacard/framework/APDU;)V;
			getTestCases()[Lbenchs/lib/templates/TestCase;;
			init([B)V;
			buildKey()V;
		}

		.packageMethodTable 0 {
		}

		.method protected <init>()V 0 {
			.stack 3;
			.locals 0;

				L0:	aload_0;
					invokespecial 9;		// benchs/lib/templates/KeyTemplateApplet.<init>()V
					aload_0;
					bspush 24;
					sconst_2;
					invokestatic 10;		// javacard/framework/JCSystem.makeTransientByteArray(SB)[B
					putfield_a 2;		// reference benchs/jcapi/javacard_security/deskey/getkey/GetKeyTestApplet.data
					return;
		}

		.method public static install([BSB)V 1 {
			.stack 2;
			.locals 0;

				L0:	new 12;		// benchs/jcapi/javacard_security/deskey/getkey/GetKeyTestApplet
					dup;
					invokespecial 13;		// benchs/jcapi/javacard_security/deskey/getkey/GetKeyTestApplet.<init>()V
					invokevirtual 14;		// register()V
					return;
		}

		.method public getTestCases()[Lbenchs/lib/templates/TestCase; 8 {
			.stack 6;
			.locals 0;

			.descriptor	Lbenchs/lib/templates/TestCase;	0.7;

				L0:	sconst_2;
					anewarray 15;		// benchs/lib/templates/TestCase
					dup;
					sconst_0;
					new 16;		// benchs/jcapi/javacard_security/deskey/getkey/GetKeyTestApplet$1
					dup;
					aload_0;
					invokespecial 17;		// benchs/jcapi/javacard_security/deskey/getkey/GetKeyTestApplet$1.<init>(Lbenchs/jcapi/javacard_security/deskey/getkey/GetKeyTestApplet;)V
					aastore;
					dup;
					sconst_1;
					new 18;		// benchs/jcapi/javacard_security/deskey/getkey/GetKeyTestApplet$2
					dup;
					aload_0;
					invokespecial 19;		// benchs/jcapi/javacard_security/deskey/getkey/GetKeyTestApplet$2.<init>(Lbenchs/jcapi/javacard_security/deskey/getkey/GetKeyTestApplet;)V
					aastore;
					areturn;
		}

		.method static access$0(Lbenchs/jcapi/javacard_security/deskey/getkey/GetKeyTestApplet;[B)V {
			.stack 2;
			.locals 0;

				L0:	aload_0;
					aload_1;
					invokevirtual 20;		// init([B)V
					return;
		}

		.method static access$1(Lbenchs/jcapi/javacard_security/deskey/getkey/GetKeyTestApplet;)Lbenchs/lib/templates/DummyInterface; {
			.stack 1;
			.locals 0;

			.descriptor	Lbenchs/lib/templates/DummyInterface;	0.1;

				L0:	aload_0;
					getfield_a 3;		// reference benchs/lib/templates/KeyTemplateApplet.dummyInterface
					areturn;
		}

		.method static access$2(Lbenchs/jcapi/javacard_security/deskey/getkey/GetKeyTestApplet;)[B {
			.stack 1;
			.locals 0;

				L0:	aload_0;
					getfield_a 2;		// reference benchs/jcapi/javacard_security/deskey/getkey/GetKeyTestApplet.data
					areturn;
		}

		.method static access$3(Lbenchs/jcapi/javacard_security/deskey/getkey/GetKeyTestApplet;)Ljavacard/security/DESKey; {
			.stack 1;
			.locals 0;

			.descriptor	Ljavacard/security/DESKey;	2.10;

				L0:	aload_0;
					getfield_a 4;		// reference benchs/lib/templates/KeyTemplateApplet.desKey
					areturn;
		}

	}

}
