// converted by version 1.3
// on Tue Nov 27 17:44:55 CET 2007

.package benchs/jcapi/javacard_security/randomdata/generatedata {
	.aid 0x4D:0x45:0x53:0x55:0x52:0x45:0x5F:0x67:0x65:0x6E:0x64:0x61:0x74:0x61;
	.version 1.0;

	.imports {
		0x4D:0x45:0x53:0x55:0x52:0x45 1.0;		//benchs/lib/templates
		0xA0:0x0:0x0:0x0:0x62:0x0:0x1 1.0;		//java/lang
		0xA0:0x0:0x0:0x0:0x62:0x1:0x1 1.0;		//javacard/framework
		0xA0:0x0:0x0:0x0:0x62:0x1:0x2 1.1;		//javacard/security
	}

	.applet {
		0x4D:0x45:0x53:0x55:0x52:0x45:0x5F:0x67:0x65:0x6E:0x64:0x61:0x74:0x61:0x1 GenerateDataTestApplet;
	}

	.constantPool {
		// 0
		instanceFieldRef GenerateDataTestApplet GenerateDataTestApplet$1/this$0;
		// 1
		instanceFieldRef GenerateDataTestApplet GenerateDataTestApplet$2/this$0;
		// 2
		instanceFieldRef GenerateDataTestApplet GenerateDataTestApplet$3/this$0;
		// 3
		instanceFieldRef GenerateDataTestApplet GenerateDataTestApplet$4/this$0;
		// 4
		instanceFieldRef byte[] GenerateDataTestApplet/data;
		// 5
		instanceFieldRef 0.5 0.11.2;		// reference benchs/lib/templates/CryptoTemplateApplet.dummy
		// 6
		instanceFieldRef 0.3 0.11.7;		// reference benchs/lib/templates/CryptoTemplateApplet.cryptoInfo
		// 7
		instanceFieldRef 3.14 0.11.6;		// reference benchs/lib/templates/CryptoTemplateApplet.random
		// 8
		staticMethodRef 0.7.0()V;		// benchs/lib/templates/TestCase.<init>()V
		// 9
		staticMethodRef GenerateDataTestApplet/access$3(Lbenchs/jcapi/javacard_security/randomdata/generatedata/GenerateDataTestApplet;[B)V;
		// 10
		staticMethodRef 2.7.1(S)V;		// javacard/framework/ISOException.throwIt(S)V
		// 11
		staticMethodRef GenerateDataTestApplet/access$4(Lbenchs/jcapi/javacard_security/randomdata/generatedata/GenerateDataTestApplet;)Ljavacard/security/RandomData;;
			.descriptor	Ljavacard/security/RandomData;	3.14;

		// 12
		virtualMethodRef 3.14.1([BSS)V;		// generateData([BSS)V
		// 13
		staticMethodRef GenerateDataTestApplet/access$0(Lbenchs/jcapi/javacard_security/randomdata/generatedata/GenerateDataTestApplet;)Lbenchs/lib/templates/DummyClass;;
			.descriptor	Lbenchs/lib/templates/DummyClass;	0.5;

		// 14
		staticMethodRef GenerateDataTestApplet/access$1(Lbenchs/jcapi/javacard_security/randomdata/generatedata/GenerateDataTestApplet;)[B;
		// 15
		staticMethodRef 0.11.0()V;		// benchs/lib/templates/CryptoTemplateApplet.<init>()V
		// 16
		staticMethodRef 2.8.13(SB)[B;		// javacard/framework/JCSystem.makeTransientByteArray(SB)[B
		// 17
		staticMethodRef GenerateDataTestApplet/access$2(Lbenchs/jcapi/javacard_security/randomdata/generatedata/GenerateDataTestApplet;)Lbenchs/lib/templates/CryptoInfo;;
			.descriptor	Lbenchs/lib/templates/CryptoInfo;	0.3;

		// 18
		classRef GenerateDataTestApplet;
		// 19
		staticMethodRef GenerateDataTestApplet/<init>()V;
		// 20
		virtualMethodRef 0.11.1()V;		// register()V
		// 21
		classRef 0.7;		// benchs/lib/templates/TestCase
		// 22
		classRef GenerateDataTestApplet$1;
		// 23
		staticMethodRef GenerateDataTestApplet$1/<init>(Lbenchs/jcapi/javacard_security/randomdata/generatedata/GenerateDataTestApplet;)V;
		// 24
		classRef GenerateDataTestApplet$2;
		// 25
		staticMethodRef GenerateDataTestApplet$2/<init>(Lbenchs/jcapi/javacard_security/randomdata/generatedata/GenerateDataTestApplet;)V;
		// 26
		classRef GenerateDataTestApplet$3;
		// 27
		staticMethodRef GenerateDataTestApplet$3/<init>(Lbenchs/jcapi/javacard_security/randomdata/generatedata/GenerateDataTestApplet;)V;
		// 28
		classRef GenerateDataTestApplet$4;
		// 29
		staticMethodRef GenerateDataTestApplet$4/<init>(Lbenchs/jcapi/javacard_security/randomdata/generatedata/GenerateDataTestApplet;)V;
		// 30
		virtualMethodRef 0.3.12()S;		// getOutOffset()S
		// 31
		virtualMethodRef 0.3.13()S;		// getOutLength()S
		// 32
		virtualMethodRef 0.11.9([B)V;		// init([B)V
		// 33
		virtualMethodRef 0.5.6([BSS)V;		// dummyMethodVoid([BSS)V
	}

	.class final GenerateDataTestApplet$1 extends 0.7 {		// extends benchs/lib/templates/TestCase

		.fields {
			final GenerateDataTestApplet this$0 0;		// Lbenchs/jcapi/javacard_security/randomdata/generatedata/GenerateDataTestApplet;
		}

		.publicMethodTable 6 {
			equals(Ljava/lang/Object;)Z;
			setUp([BS)V;
			setUp([B)V;
			cleanUp([B)V;
			isUseInnerCounter()Z;
			setUseInnerCounter(Z)V;
			run([B)V;
		}

		.packageMethodTable 0 {
		}

		.method  <init>(Lbenchs/jcapi/javacard_security/randomdata/generatedata/GenerateDataTestApplet;)V {
			.stack 2;
			.locals 0;

				L0:	aload_0;
					aload_1;
					putfield_a 0;		// reference benchs/jcapi/javacard_security/randomdata/generatedata/GenerateDataTestApplet$1.this$0
					aload_0;
					invokespecial 8;		// benchs/lib/templates/TestCase.<init>()V
					return;
		}

		.method public run([B)V 6 {
			.stack 4;
			.locals 0;

				L0:	getfield_a_this 0;		// reference benchs/jcapi/javacard_security/randomdata/generatedata/GenerateDataTestApplet$1.this$0
					invokestatic 13;		// benchs/jcapi/javacard_security/randomdata/generatedata/GenerateDataTestApplet.access$0(Lbenchs/jcapi/javacard_security/randomdata/generatedata/GenerateDataTestApplet;)Lbenchs/lib/templates/DummyClass;
					getfield_a_this 0;		// reference benchs/jcapi/javacard_security/randomdata/generatedata/GenerateDataTestApplet$1.this$0
					invokestatic 14;		// benchs/jcapi/javacard_security/randomdata/generatedata/GenerateDataTestApplet.access$1(Lbenchs/jcapi/javacard_security/randomdata/generatedata/GenerateDataTestApplet;)[B
					getfield_a_this 0;		// reference benchs/jcapi/javacard_security/randomdata/generatedata/GenerateDataTestApplet$1.this$0
					invokestatic 17;		// benchs/jcapi/javacard_security/randomdata/generatedata/GenerateDataTestApplet.access$2(Lbenchs/jcapi/javacard_security/randomdata/generatedata/GenerateDataTestApplet;)Lbenchs/lib/templates/CryptoInfo;
					invokevirtual 30;		// getOutOffset()S
					getfield_a_this 0;		// reference benchs/jcapi/javacard_security/randomdata/generatedata/GenerateDataTestApplet$1.this$0
					invokestatic 17;		// benchs/jcapi/javacard_security/randomdata/generatedata/GenerateDataTestApplet.access$2(Lbenchs/jcapi/javacard_security/randomdata/generatedata/GenerateDataTestApplet;)Lbenchs/lib/templates/CryptoInfo;
					invokevirtual 31;		// getOutLength()S
					invokevirtual 33;		// dummyMethodVoid([BSS)V
					return;
		}

	}

	.class final GenerateDataTestApplet$2 extends 0.7 {		// extends benchs/lib/templates/TestCase

		.fields {
			final GenerateDataTestApplet this$0 0;		// Lbenchs/jcapi/javacard_security/randomdata/generatedata/GenerateDataTestApplet;
		}

		.publicMethodTable 2 {
			equals(Ljava/lang/Object;)Z;
			setUp([BS)V;
			setUp([B)V;
			cleanUp([B)V;
			isUseInnerCounter()Z;
			setUseInnerCounter(Z)V;
			run([B)V;
		}

		.packageMethodTable 0 {
		}

		.method  <init>(Lbenchs/jcapi/javacard_security/randomdata/generatedata/GenerateDataTestApplet;)V {
			.stack 2;
			.locals 0;

				L0:	aload_0;
					aload_1;
					putfield_a 1;		// reference benchs/jcapi/javacard_security/randomdata/generatedata/GenerateDataTestApplet$2.this$0
					aload_0;
					invokespecial 8;		// benchs/lib/templates/TestCase.<init>()V
					return;
		}

		.method public setUp([B)V 2 {
			.stack 2;
			.locals 0;

				L0:	getfield_a_this 1;		// reference benchs/jcapi/javacard_security/randomdata/generatedata/GenerateDataTestApplet$2.this$0
					aload_1;
					invokestatic 9;		// benchs/jcapi/javacard_security/randomdata/generatedata/GenerateDataTestApplet.access$3(Lbenchs/jcapi/javacard_security/randomdata/generatedata/GenerateDataTestApplet;[B)V
					getfield_a_this 1;		// reference benchs/jcapi/javacard_security/randomdata/generatedata/GenerateDataTestApplet$2.this$0
					invokestatic 17;		// benchs/jcapi/javacard_security/randomdata/generatedata/GenerateDataTestApplet.access$2(Lbenchs/jcapi/javacard_security/randomdata/generatedata/GenerateDataTestApplet;)Lbenchs/lib/templates/CryptoInfo;
					invokevirtual 30;		// getOutOffset()S
					getfield_a_this 1;		// reference benchs/jcapi/javacard_security/randomdata/generatedata/GenerateDataTestApplet$2.this$0
					invokestatic 17;		// benchs/jcapi/javacard_security/randomdata/generatedata/GenerateDataTestApplet.access$2(Lbenchs/jcapi/javacard_security/randomdata/generatedata/GenerateDataTestApplet;)Lbenchs/lib/templates/CryptoInfo;
					invokevirtual 31;		// getOutLength()S
					sadd;
					getfield_a_this 1;		// reference benchs/jcapi/javacard_security/randomdata/generatedata/GenerateDataTestApplet$2.this$0
					invokestatic 14;		// benchs/jcapi/javacard_security/randomdata/generatedata/GenerateDataTestApplet.access$1(Lbenchs/jcapi/javacard_security/randomdata/generatedata/GenerateDataTestApplet;)[B
					arraylength;
					if_scmple L2;
				L1:	sspush 27012;
					invokestatic 10;		// javacard/framework/ISOException.throwIt(S)V
				L2:	return;
		}

		.method public run([B)V 6 {
			.stack 4;
			.locals 0;

				L0:	getfield_a_this 1;		// reference benchs/jcapi/javacard_security/randomdata/generatedata/GenerateDataTestApplet$2.this$0
					invokestatic 11;		// benchs/jcapi/javacard_security/randomdata/generatedata/GenerateDataTestApplet.access$4(Lbenchs/jcapi/javacard_security/randomdata/generatedata/GenerateDataTestApplet;)Ljavacard/security/RandomData;
					getfield_a_this 1;		// reference benchs/jcapi/javacard_security/randomdata/generatedata/GenerateDataTestApplet$2.this$0
					invokestatic 14;		// benchs/jcapi/javacard_security/randomdata/generatedata/GenerateDataTestApplet.access$1(Lbenchs/jcapi/javacard_security/randomdata/generatedata/GenerateDataTestApplet;)[B
					getfield_a_this 1;		// reference benchs/jcapi/javacard_security/randomdata/generatedata/GenerateDataTestApplet$2.this$0
					invokestatic 17;		// benchs/jcapi/javacard_security/randomdata/generatedata/GenerateDataTestApplet.access$2(Lbenchs/jcapi/javacard_security/randomdata/generatedata/GenerateDataTestApplet;)Lbenchs/lib/templates/CryptoInfo;
					invokevirtual 30;		// getOutOffset()S
					getfield_a_this 1;		// reference benchs/jcapi/javacard_security/randomdata/generatedata/GenerateDataTestApplet$2.this$0
					invokestatic 17;		// benchs/jcapi/javacard_security/randomdata/generatedata/GenerateDataTestApplet.access$2(Lbenchs/jcapi/javacard_security/randomdata/generatedata/GenerateDataTestApplet;)Lbenchs/lib/templates/CryptoInfo;
					invokevirtual 31;		// getOutLength()S
					invokevirtual 12;		// generateData([BSS)V
					return;
		}

	}

	.class final GenerateDataTestApplet$3 extends 0.7 {		// extends benchs/lib/templates/TestCase

		.fields {
			final GenerateDataTestApplet this$0 0;		// Lbenchs/jcapi/javacard_security/randomdata/generatedata/GenerateDataTestApplet;
		}

		.publicMethodTable 6 {
			equals(Ljava/lang/Object;)Z;
			setUp([BS)V;
			setUp([B)V;
			cleanUp([B)V;
			isUseInnerCounter()Z;
			setUseInnerCounter(Z)V;
			run([B)V;
		}

		.packageMethodTable 0 {
		}

		.method  <init>(Lbenchs/jcapi/javacard_security/randomdata/generatedata/GenerateDataTestApplet;)V {
			.stack 2;
			.locals 0;

				L0:	aload_0;
					aload_1;
					putfield_a 2;		// reference benchs/jcapi/javacard_security/randomdata/generatedata/GenerateDataTestApplet$3.this$0
					aload_0;
					invokespecial 8;		// benchs/lib/templates/TestCase.<init>()V
					return;
		}

		.method public run([B)V 6 {
			.stack 4;
			.locals 0;

				L0:	getfield_a_this 2;		// reference benchs/jcapi/javacard_security/randomdata/generatedata/GenerateDataTestApplet$3.this$0
					invokestatic 13;		// benchs/jcapi/javacard_security/randomdata/generatedata/GenerateDataTestApplet.access$0(Lbenchs/jcapi/javacard_security/randomdata/generatedata/GenerateDataTestApplet;)Lbenchs/lib/templates/DummyClass;
					aload_1;
					getfield_a_this 2;		// reference benchs/jcapi/javacard_security/randomdata/generatedata/GenerateDataTestApplet$3.this$0
					invokestatic 17;		// benchs/jcapi/javacard_security/randomdata/generatedata/GenerateDataTestApplet.access$2(Lbenchs/jcapi/javacard_security/randomdata/generatedata/GenerateDataTestApplet;)Lbenchs/lib/templates/CryptoInfo;
					invokevirtual 30;		// getOutOffset()S
					getfield_a_this 2;		// reference benchs/jcapi/javacard_security/randomdata/generatedata/GenerateDataTestApplet$3.this$0
					invokestatic 17;		// benchs/jcapi/javacard_security/randomdata/generatedata/GenerateDataTestApplet.access$2(Lbenchs/jcapi/javacard_security/randomdata/generatedata/GenerateDataTestApplet;)Lbenchs/lib/templates/CryptoInfo;
					invokevirtual 31;		// getOutLength()S
					invokevirtual 33;		// dummyMethodVoid([BSS)V
					return;
		}

	}

	.class final GenerateDataTestApplet$4 extends 0.7 {		// extends benchs/lib/templates/TestCase

		.fields {
			final GenerateDataTestApplet this$0 0;		// Lbenchs/jcapi/javacard_security/randomdata/generatedata/GenerateDataTestApplet;
		}

		.publicMethodTable 2 {
			equals(Ljava/lang/Object;)Z;
			setUp([BS)V;
			setUp([B)V;
			cleanUp([B)V;
			isUseInnerCounter()Z;
			setUseInnerCounter(Z)V;
			run([B)V;
		}

		.packageMethodTable 0 {
		}

		.method  <init>(Lbenchs/jcapi/javacard_security/randomdata/generatedata/GenerateDataTestApplet;)V {
			.stack 2;
			.locals 0;

				L0:	aload_0;
					aload_1;
					putfield_a 3;		// reference benchs/jcapi/javacard_security/randomdata/generatedata/GenerateDataTestApplet$4.this$0
					aload_0;
					invokespecial 8;		// benchs/lib/templates/TestCase.<init>()V
					return;
		}

		.method public setUp([B)V 2 {
			.stack 2;
			.locals 0;

				L0:	getfield_a_this 3;		// reference benchs/jcapi/javacard_security/randomdata/generatedata/GenerateDataTestApplet$4.this$0
					aload_1;
					invokestatic 9;		// benchs/jcapi/javacard_security/randomdata/generatedata/GenerateDataTestApplet.access$3(Lbenchs/jcapi/javacard_security/randomdata/generatedata/GenerateDataTestApplet;[B)V
					getfield_a_this 3;		// reference benchs/jcapi/javacard_security/randomdata/generatedata/GenerateDataTestApplet$4.this$0
					invokestatic 17;		// benchs/jcapi/javacard_security/randomdata/generatedata/GenerateDataTestApplet.access$2(Lbenchs/jcapi/javacard_security/randomdata/generatedata/GenerateDataTestApplet;)Lbenchs/lib/templates/CryptoInfo;
					invokevirtual 30;		// getOutOffset()S
					getfield_a_this 3;		// reference benchs/jcapi/javacard_security/randomdata/generatedata/GenerateDataTestApplet$4.this$0
					invokestatic 17;		// benchs/jcapi/javacard_security/randomdata/generatedata/GenerateDataTestApplet.access$2(Lbenchs/jcapi/javacard_security/randomdata/generatedata/GenerateDataTestApplet;)Lbenchs/lib/templates/CryptoInfo;
					invokevirtual 31;		// getOutLength()S
					sadd;
					aload_1;
					arraylength;
					if_scmple L2;
				L1:	sspush 27012;
					invokestatic 10;		// javacard/framework/ISOException.throwIt(S)V
				L2:	return;
		}

		.method public run([B)V 6 {
			.stack 4;
			.locals 0;

				L0:	getfield_a_this 3;		// reference benchs/jcapi/javacard_security/randomdata/generatedata/GenerateDataTestApplet$4.this$0
					invokestatic 11;		// benchs/jcapi/javacard_security/randomdata/generatedata/GenerateDataTestApplet.access$4(Lbenchs/jcapi/javacard_security/randomdata/generatedata/GenerateDataTestApplet;)Ljavacard/security/RandomData;
					aload_1;
					getfield_a_this 3;		// reference benchs/jcapi/javacard_security/randomdata/generatedata/GenerateDataTestApplet$4.this$0
					invokestatic 17;		// benchs/jcapi/javacard_security/randomdata/generatedata/GenerateDataTestApplet.access$2(Lbenchs/jcapi/javacard_security/randomdata/generatedata/GenerateDataTestApplet;)Lbenchs/lib/templates/CryptoInfo;
					invokevirtual 30;		// getOutOffset()S
					getfield_a_this 3;		// reference benchs/jcapi/javacard_security/randomdata/generatedata/GenerateDataTestApplet$4.this$0
					invokestatic 17;		// benchs/jcapi/javacard_security/randomdata/generatedata/GenerateDataTestApplet.access$2(Lbenchs/jcapi/javacard_security/randomdata/generatedata/GenerateDataTestApplet;)Lbenchs/lib/templates/CryptoInfo;
					invokevirtual 31;		// getOutLength()S
					invokevirtual 12;		// generateData([BSS)V
					return;
		}

	}

	.class public GenerateDataTestApplet 0 extends 0.11 {		// extends benchs/lib/templates/CryptoTemplateApplet

		.fields {
			private byte[] data 0;		// [B
		}

		.publicMethodTable 8 {
			equals(Ljava/lang/Object;)Z;
			register()V;
			register([BSB)V;
			selectingApplet()Z;
			deselect()V;
			getShareableInterfaceObject(Ljavacard/framework/AID;B)Ljavacard/framework/Shareable;;
			select()Z;
			process(Ljavacard/framework/APDU;)V;
			getTestCases()[Lbenchs/lib/templates/TestCase;;
			init([B)V;
			buildKey()V;
		}

		.packageMethodTable 0 {
		}

		.method private <init>()V {
			.stack 3;
			.locals 0;

				L0:	aload_0;
					invokespecial 15;		// benchs/lib/templates/CryptoTemplateApplet.<init>()V
					aload_0;
					sspush 200;
					sconst_2;
					invokestatic 16;		// javacard/framework/JCSystem.makeTransientByteArray(SB)[B
					putfield_a 4;		// reference benchs/jcapi/javacard_security/randomdata/generatedata/GenerateDataTestApplet.data
					return;
		}

		.method public static install([BSB)V 0 {
			.stack 2;
			.locals 0;

				L0:	new 18;		// benchs/jcapi/javacard_security/randomdata/generatedata/GenerateDataTestApplet
					dup;
					invokespecial 19;		// benchs/jcapi/javacard_security/randomdata/generatedata/GenerateDataTestApplet.<init>()V
					invokevirtual 20;		// register()V
					return;
		}

		.method public getTestCases()[Lbenchs/lib/templates/TestCase; 8 {
			.stack 6;
			.locals 0;

			.descriptor	Lbenchs/lib/templates/TestCase;	0.7;

				L0:	sconst_4;
					anewarray 21;		// benchs/lib/templates/TestCase
					dup;
					sconst_0;
					new 22;		// benchs/jcapi/javacard_security/randomdata/generatedata/GenerateDataTestApplet$1
					dup;
					aload_0;
					invokespecial 23;		// benchs/jcapi/javacard_security/randomdata/generatedata/GenerateDataTestApplet$1.<init>(Lbenchs/jcapi/javacard_security/randomdata/generatedata/GenerateDataTestApplet;)V
					aastore;
					dup;
					sconst_1;
					new 24;		// benchs/jcapi/javacard_security/randomdata/generatedata/GenerateDataTestApplet$2
					dup;
					aload_0;
					invokespecial 25;		// benchs/jcapi/javacard_security/randomdata/generatedata/GenerateDataTestApplet$2.<init>(Lbenchs/jcapi/javacard_security/randomdata/generatedata/GenerateDataTestApplet;)V
					aastore;
					dup;
					sconst_2;
					new 26;		// benchs/jcapi/javacard_security/randomdata/generatedata/GenerateDataTestApplet$3
					dup;
					aload_0;
					invokespecial 27;		// benchs/jcapi/javacard_security/randomdata/generatedata/GenerateDataTestApplet$3.<init>(Lbenchs/jcapi/javacard_security/randomdata/generatedata/GenerateDataTestApplet;)V
					aastore;
					dup;
					sconst_3;
					new 28;		// benchs/jcapi/javacard_security/randomdata/generatedata/GenerateDataTestApplet$4
					dup;
					aload_0;
					invokespecial 29;		// benchs/jcapi/javacard_security/randomdata/generatedata/GenerateDataTestApplet$4.<init>(Lbenchs/jcapi/javacard_security/randomdata/generatedata/GenerateDataTestApplet;)V
					aastore;
					areturn;
		}

		.method static access$0(Lbenchs/jcapi/javacard_security/randomdata/generatedata/GenerateDataTestApplet;)Lbenchs/lib/templates/DummyClass; {
			.stack 1;
			.locals 0;

			.descriptor	Lbenchs/lib/templates/DummyClass;	0.5;

				L0:	aload_0;
					getfield_a 5;		// reference benchs/lib/templates/CryptoTemplateApplet.dummy
					areturn;
		}

		.method static access$1(Lbenchs/jcapi/javacard_security/randomdata/generatedata/GenerateDataTestApplet;)[B {
			.stack 1;
			.locals 0;

				L0:	aload_0;
					getfield_a 4;		// reference benchs/jcapi/javacard_security/randomdata/generatedata/GenerateDataTestApplet.data
					areturn;
		}

		.method static access$2(Lbenchs/jcapi/javacard_security/randomdata/generatedata/GenerateDataTestApplet;)Lbenchs/lib/templates/CryptoInfo; {
			.stack 1;
			.locals 0;

			.descriptor	Lbenchs/lib/templates/CryptoInfo;	0.3;

				L0:	aload_0;
					getfield_a 6;		// reference benchs/lib/templates/CryptoTemplateApplet.cryptoInfo
					areturn;
		}

		.method static access$3(Lbenchs/jcapi/javacard_security/randomdata/generatedata/GenerateDataTestApplet;[B)V {
			.stack 2;
			.locals 0;

				L0:	aload_0;
					aload_1;
					invokevirtual 32;		// init([B)V
					return;
		}

		.method static access$4(Lbenchs/jcapi/javacard_security/randomdata/generatedata/GenerateDataTestApplet;)Ljavacard/security/RandomData; {
			.stack 1;
			.locals 0;

			.descriptor	Ljavacard/security/RandomData;	3.14;

				L0:	aload_0;
					getfield_a 7;		// reference benchs/lib/templates/CryptoTemplateApplet.random
					areturn;
		}

	}

}
