// converted by version 1.3
// on Mon Nov 26 16:41:31 CET 2007

.package benchs/jcapi/javacard_framework/jcsystem/begincommittransaction {
	.aid 0x4D:0x45:0x53:0x55:0x52:0x45:0x5F:0x73:0x79:0x73:0x74:0x72:0x61:0x6E:0x73;
	.version 1.0;

	.imports {
		0x4D:0x45:0x53:0x55:0x52:0x45 1.0;		//benchs/lib/templates
		0xA0:0x0:0x0:0x0:0x62:0x0:0x1 1.0;		//java/lang
		0xA0:0x0:0x0:0x0:0x62:0x1:0x1 1.0;		//javacard/framework
	}

	.applet {
		0x4D:0x45:0x53:0x55:0x52:0x45:0x5F:0x73:0x79:0x73:0x74:0x72:0x61:0x6E:0x73:0x1 BeginCommitTransactionTestApplet;
	}

	.constantPool {
		// 0
		instanceFieldRef BeginCommitTransactionTestApplet BeginCommitTransactionTestApplet$1/this$0;
		// 1
		instanceFieldRef BeginCommitTransactionTestApplet BeginCommitTransactionTestApplet$2/this$0;
		// 2
		staticMethodRef 0.5.7()V;		// benchs/lib/templates/DummyClass.dummyMethodStaticVoid()V
		// 3
		staticMethodRef 0.7.0()V;		// benchs/lib/templates/TestCase.<init>()V
		// 4
		staticMethodRef 2.8.1()V;		// javacard/framework/JCSystem.beginTransaction()V
		// 5
		staticMethodRef 2.8.2()V;		// javacard/framework/JCSystem.commitTransaction()V
		// 6
		staticMethodRef 0.4.0()V;		// benchs/lib/templates/TemplateApplet.<init>()V
		// 7
		classRef BeginCommitTransactionTestApplet;
		// 8
		staticMethodRef BeginCommitTransactionTestApplet/<init>()V;
		// 9
		virtualMethodRef 0.4.1()V;		// register()V
		// 10
		classRef 0.7;		// benchs/lib/templates/TestCase
		// 11
		classRef BeginCommitTransactionTestApplet$1;
		// 12
		staticMethodRef BeginCommitTransactionTestApplet$1/<init>(Lbenchs/jcapi/javacard_framework/jcsystem/begincommittransaction/BeginCommitTransactionTestApplet;)V;
		// 13
		classRef BeginCommitTransactionTestApplet$2;
		// 14
		staticMethodRef BeginCommitTransactionTestApplet$2/<init>(Lbenchs/jcapi/javacard_framework/jcsystem/begincommittransaction/BeginCommitTransactionTestApplet;)V;
	}

	.class final BeginCommitTransactionTestApplet$1 extends 0.7 {		// extends benchs/lib/templates/TestCase

		.fields {
			final BeginCommitTransactionTestApplet this$0 0;		// Lbenchs/jcapi/javacard_framework/jcsystem/begincommittransaction/BeginCommitTransactionTestApplet;
		}

		.publicMethodTable 6 {
			equals(Ljava/lang/Object;)Z;
			setUp([BS)V;
			setUp([B)V;
			cleanUp([B)V;
			isUseInnerCounter()Z;
			setUseInnerCounter(Z)V;
			run([B)V;
		}

		.packageMethodTable 0 {
		}

		.method  <init>(Lbenchs/jcapi/javacard_framework/jcsystem/begincommittransaction/BeginCommitTransactionTestApplet;)V {
			.stack 2;
			.locals 0;

				L0:	aload_0;
					aload_1;
					putfield_a 0;		// reference benchs/jcapi/javacard_framework/jcsystem/begincommittransaction/BeginCommitTransactionTestApplet$1.this$0
					aload_0;
					invokespecial 3;		// benchs/lib/templates/TestCase.<init>()V
					return;
		}

		.method public run([B)V 6 {
			.stack 0;
			.locals 0;

				L0:	invokestatic 2;		// benchs/lib/templates/DummyClass.dummyMethodStaticVoid()V
					invokestatic 2;		// benchs/lib/templates/DummyClass.dummyMethodStaticVoid()V
					return;
		}

	}

	.class final BeginCommitTransactionTestApplet$2 extends 0.7 {		// extends benchs/lib/templates/TestCase

		.fields {
			final BeginCommitTransactionTestApplet this$0 0;		// Lbenchs/jcapi/javacard_framework/jcsystem/begincommittransaction/BeginCommitTransactionTestApplet;
		}

		.publicMethodTable 6 {
			equals(Ljava/lang/Object;)Z;
			setUp([BS)V;
			setUp([B)V;
			cleanUp([B)V;
			isUseInnerCounter()Z;
			setUseInnerCounter(Z)V;
			run([B)V;
		}

		.packageMethodTable 0 {
		}

		.method  <init>(Lbenchs/jcapi/javacard_framework/jcsystem/begincommittransaction/BeginCommitTransactionTestApplet;)V {
			.stack 2;
			.locals 0;

				L0:	aload_0;
					aload_1;
					putfield_a 1;		// reference benchs/jcapi/javacard_framework/jcsystem/begincommittransaction/BeginCommitTransactionTestApplet$2.this$0
					aload_0;
					invokespecial 3;		// benchs/lib/templates/TestCase.<init>()V
					return;
		}

		.method public run([B)V 6 {
			.stack 0;
			.locals 0;

				L0:	invokestatic 4;		// javacard/framework/JCSystem.beginTransaction()V
					invokestatic 5;		// javacard/framework/JCSystem.commitTransaction()V
					return;
		}

	}

	.class public BeginCommitTransactionTestApplet 0 extends 0.4 {		// extends benchs/lib/templates/TemplateApplet

		.publicMethodTable 8 {
			equals(Ljava/lang/Object;)Z;
			register()V;
			register([BSB)V;
			selectingApplet()Z;
			deselect()V;
			getShareableInterfaceObject(Ljavacard/framework/AID;B)Ljavacard/framework/Shareable;;
			select()Z;
			process(Ljavacard/framework/APDU;)V;
			getTestCases()[Lbenchs/lib/templates/TestCase;;
		}

		.packageMethodTable 0 {
		}

		.method public <init>()V 0 {
			.stack 1;
			.locals 0;

				L0:	aload_0;
					invokespecial 6;		// benchs/lib/templates/TemplateApplet.<init>()V
					return;
		}

		.method public static install([BSB)V 1 {
			.stack 2;
			.locals 0;

				L0:	new 7;		// benchs/jcapi/javacard_framework/jcsystem/begincommittransaction/BeginCommitTransactionTestApplet
					dup;
					invokespecial 8;		// benchs/jcapi/javacard_framework/jcsystem/begincommittransaction/BeginCommitTransactionTestApplet.<init>()V
					invokevirtual 9;		// register()V
					return;
		}

		.method public getTestCases()[Lbenchs/lib/templates/TestCase; 8 {
			.stack 6;
			.locals 0;

			.descriptor	Lbenchs/lib/templates/TestCase;	0.7;

				L0:	sconst_2;
					anewarray 10;		// benchs/lib/templates/TestCase
					dup;
					sconst_0;
					new 11;		// benchs/jcapi/javacard_framework/jcsystem/begincommittransaction/BeginCommitTransactionTestApplet$1
					dup;
					aload_0;
					invokespecial 12;		// benchs/jcapi/javacard_framework/jcsystem/begincommittransaction/BeginCommitTransactionTestApplet$1.<init>(Lbenchs/jcapi/javacard_framework/jcsystem/begincommittransaction/BeginCommitTransactionTestApplet;)V
					aastore;
					dup;
					sconst_1;
					new 13;		// benchs/jcapi/javacard_framework/jcsystem/begincommittransaction/BeginCommitTransactionTestApplet$2
					dup;
					aload_0;
					invokespecial 14;		// benchs/jcapi/javacard_framework/jcsystem/begincommittransaction/BeginCommitTransactionTestApplet$2.<init>(Lbenchs/jcapi/javacard_framework/jcsystem/begincommittransaction/BeginCommitTransactionTestApplet;)V
					aastore;
					areturn;
		}

	}

}
